[
	{
		"name":"小说","url":"https://m.douban.com/book/novel"
	},
	{
		"name":"爱情","url":"https://m.douban.com/book/love"
	},
	{
		"name":"历史","url":"https://m.douban.com/book/history"
	},
	{
		"name":"外国文学","url":"https://m.douban.com/book/foreign"
	},
	{
		"name":"青春","url":"https://m.douban.com/book/youth"
	},
	{
		"name":"励志","url":"https://m.douban.com/book/motivation"
	},
	{
		"name":"随笔","url":"https://m.douban.com/book/essay"
	},
	{
		"name":"传记","url":"https://m.douban.com/book/bio"
	},
	{
		"name":"推理","url":"https://m.douban.com/book/detective"
	},
	{
		"name":"旅行","url":"https://m.douban.com/book/travel"
	},	
	{
		"name":"奇幻","url":"https://m.douban.com/book/fantasy"
	},
	{
		"name":"经管","url":"https://m.douban.com/book/business"
	}
]